bayesnet/__init__.py
bayesnet/abc.py
bayesnet/base.py
bayesnet/core.py
bayesnet/junction.py
bayesnet/opencl.py
bayesnet/pmf.py
bayesnet/testing.py
bayesnet/utils.py
bayesnet_marginals-0.0.4.data/data/config/bayesnet.json
bayesnet_marginals-0.0.4.dist-info/METADATA
bayesnet_marginals-0.0.4.dist-info/RECORD
bayesnet_marginals-0.0.4.dist-info/WHEEL
bayesnet_marginals-0.0.4.dist-info/top_level.txt
